Metadata-Version: 2.1
Name: arimionim-math
Version: 0.0.3
Summary: Arimionim's example Python package
Home-page: https://github.com/abc/xyz
Author: Arslan Aknazarov
Author-email: abc@xyz.ru
License: BSD 2-clause
Platform: UNKNOWN
Classifier: Development Status :: 1 - Planning
Classifier: Intended Audience :: Science/Research
Classifier: License :: OSI Approved :: BSD License
Classifier: Operating System :: POSIX :: Linux
Classifier: Programming Language :: Python :: 2
Classifier: Programming Language :: Python :: 2.7
Classifier: Programming Language :: Python :: 3
Classifier: Programming Language :: Python :: 3.4
Classifier: Programming Language :: Python :: 3.5
